tulona/__init__.py
tulona/exceptions.py
tulona/adapter/bigquery.py
tulona/adapter/connection.py
tulona/adapter/mssql.py
tulona/adapter/mysql.py
tulona/adapter/postgres.py
tulona/adapter/snowflake.py
tulona/adapter/base/connection.py
tulona/cli/base.py
tulona/cli/params.py
tulona/config/__init__.py
tulona/config/profile.py
tulona/config/project.py
tulona/task/base.py
tulona/task/compare.py
tulona/task/helper.py
tulona/task/ping.py
tulona/task/profile.py
tulona/task/scan.py
tulona/util/__init__.py
tulona/util/database.py
tulona/util/dataframe.py
tulona/util/excel.py
tulona/util/filesystem.py
tulona/util/profiles.py
tulona/util/sql.py
tulona/util/yaml_parser.py
tulona-0.12.0.dist-info/licenses/LICENSE
tulona-0.12.0.dist-info/METADATA
tulona-0.12.0.dist-info/WHEEL
tulona-0.12.0.dist-info/entry_points.txt
tulona-0.12.0.dist-info/top_level.txt
tulona-0.12.0.dist-info/RECORD
