Metadata-Version: 2.4
Name: tulona
Version: 0.12.0
Summary: A tool to compare data from different sources.
Author: Mrinal Kanti Sardar
Project-URL: Homepage, https://github.com/mrinalsardar/tulona
Project-URL: Documentation, https://github.com/mrinalsardar/tulona
Project-URL: Repository, https://github.com/mrinalsardar/tulona.git
Project-URL: Issues, https://github.com/mrinalsardar/tulona/issues
Keywords: tulona,comparison,data comparison,database scan,database profile
Classifier: Development Status :: 3 - Alpha
Classifier: Intended Audience :: Developers
Classifier: License :: OSI Approved :: Apache Software License
Classifier: Programming Language :: Python :: 3
Classifier: Programming Language :: Python :: 3.8
Classifier: Programming Language :: Python :: 3.9
Classifier: Programming Language :: Python :: 3.10
Classifier: Programming Language :: Python :: 3.11
Requires-Python: >=3.8
License-File: LICENSE
Requires-Dist: click~=8.1
Requires-Dist: ruamel.yaml~=0.18
Requires-Dist: psycopg2-binary~=2.9
Requires-Dist: pymysql~=1.1
Requires-Dist: cryptography~=42.0
Requires-Dist: snowflake-sqlalchemy==1.5.3
Requires-Dist: snowflake-connector-python[secure-local-storage]==3.12.2
Requires-Dist: pyodbc~=5.1
Requires-Dist: pymssql==2.3.1
Requires-Dist: pandas~=1.5
Requires-Dist: numpy==1.26.4
Requires-Dist: openpyxl~=3.1
Requires-Dist: Jinja2~=3.1
Requires-Dist: pydantic~=2.7
Requires-Dist: sqlalchemy-bigquery
Requires-Dist: google-cloud-bigquery-storage
Provides-Extra: dev
Requires-Dist: pytest; extra == "dev"
Requires-Dist: flake8; extra == "dev"
Requires-Dist: coverage; extra == "dev"
Requires-Dist: black; extra == "dev"
Requires-Dist: isort; extra == "dev"
Requires-Dist: pytest-cov; extra == "dev"
Requires-Dist: faker; extra == "dev"
Requires-Dist: bump-my-version; extra == "dev"
Requires-Dist: build; extra == "dev"
Requires-Dist: twine; extra == "dev"
Dynamic: license-file
